homeconnect_watcher/__init__.py
homeconnect_watcher/_version.py
homeconnect_watcher/api.py
homeconnect_watcher/cli.py
homeconnect_watcher/event.py
homeconnect_watcher/exceptions.py
homeconnect_watcher/read.py
homeconnect_watcher/trigger.py
homeconnect_watcher/client/__init__.py
homeconnect_watcher/client/appliance.py
homeconnect_watcher/client/client.py
homeconnect_watcher/db/__init__.py
homeconnect_watcher/db/client.py
homeconnect_watcher/db/utils.py
homeconnect_watcher/db/view.py
homeconnect_watcher/exporter/__init__.py
homeconnect_watcher/exporter/base.py
homeconnect_watcher/exporter/file.py
homeconnect_watcher/exporter/postgres.py
homeconnect_watcher/sql/0_appliances.sql
homeconnect_watcher/sql/1_events.sql
homeconnect_watcher/sql/2_raw_events_active.sql
homeconnect_watcher/sql/3_raw_events_with_session_id.sql
homeconnect_watcher/sql/4_sessions.sql
homeconnect_watcher/utils/__init__.py
homeconnect_watcher/utils/logging.py
homeconnect_watcher/utils/metrics.py
homeconnect_watcher/utils/retry.py
homeconnect_watcher/utils/timeout.py
homeconnect_watcher-0.0.13.dist-info/LICENSE
homeconnect_watcher-0.0.13.dist-info/METADATA
homeconnect_watcher-0.0.13.dist-info/WHEEL
homeconnect_watcher-0.0.13.dist-info/entry_points.txt
homeconnect_watcher-0.0.13.dist-info/top_level.txt
homeconnect_watcher-0.0.13.dist-info/RECORD
