Metadata-Version: 2.1
Name: homeconnect-watcher
Version: 0.0.13
Summary: Python service that listens to HomeConnect event and logs them.
Author-email: Rogier van der Geer <rogier@vander-geer.nl>
License: MIT
Classifier: Programming Language :: Python :: 3
Requires-Python: >=3.10
License-File: LICENSE
Requires-Dist: authlib >=1.2.0
Requires-Dist: fastapi >=0.92.0
Requires-Dist: python-dotenv >=0.21.1
Requires-Dist: psycopg[binary] >=3.1.16
Requires-Dist: requests >=2.28.2
Requires-Dist: httpx >=0.23.3
Requires-Dist: typer >=0.7.0
Requires-Dist: uvicorn >=0.20.0
Requires-Dist: tqdm
Provides-Extra: dev
Requires-Dist: pre-commit >=3.6.2 ; extra == 'dev'
Requires-Dist: pytest >=7.2.1 ; extra == 'dev'
Requires-Dist: pytest-asyncio >=0.20.3 ; extra == 'dev'
Requires-Dist: pytest-mock >=3.10.0 ; extra == 'dev'
Requires-Dist: pytest-postgresql >=5.0.0 ; extra == 'dev'
Provides-Extra: prometheus
Requires-Dist: prometheus-client >=0.16.0 ; extra == 'prometheus'
